pdf_view/__init__.py
pdf_view/apps.py
pdf_view/context_managers.py
pdf_view/decorators.py
pdf_view/pdf.py
pdf_view/static/pdf_view/css/pdf.css
pdf_view/templates/pdf_view/pdf.html
pdf_view/templatetags/__init__.py
pdf_view/templatetags/svg.py
pdf_view/tests/__init__.py
pdf_view/tests/test_pdf.py
pdf_view/tests/test_pdf_view.py
pdf_view/tests/test_render_css.py
pdf_view/tests/test_svg_template_tag.py
pdf_view/tests/test_tmp_env_var.py
pdf_view/tests/test_with_tmp_env_var.py
pdf_view/utils.py
pdf_view/views.py
django_pdf_view-3.1.3.dist-info/LICENSE
django_pdf_view-3.1.3.dist-info/METADATA
django_pdf_view-3.1.3.dist-info/WHEEL
django_pdf_view-3.1.3.dist-info/RECORD
