Metadata-Version: 2.1
Name: django-pdf-view
Version: 3.1.3
Summary: Django app for seamlessly displaying and downloading PDF documents in browser
License: MIT
Keywords: pdf,pdf view,django pdf,django pdf view,generate pdf,django generate pdf
Author: Miloš Roknić
Author-email: roknic.milos.994@gmail.com
Maintainer: Miloš Roknić
Maintainer-email: roknic.milos.994@gmail.com
Requires-Python: >=3.10,<4.0
Classifier: Environment :: Web Environment
Classifier: Framework :: Django
Classifier: Framework :: Django :: 4.0
Classifier: Framework :: Django :: 5.0
Classifier: Intended Audience :: Developers
Classifier: License :: OSI Approved :: MIT License
Classifier: Operating System :: OS Independent
Classifier: Programming Language :: Python :: 3
Classifier: Programming Language :: Python :: 3.10
Classifier: Programming Language :: Python :: 3.11
Classifier: Programming Language :: Python :: 3.12
Classifier: Topic :: Software Development :: Libraries :: Application Frameworks
Classifier: Topic :: Software Development :: Libraries :: Python Modules
Requires-Dist: django (>=5.1.1,<6.0.0)
Requires-Dist: pdfkit (>=1.0.0,<2.0.0)
Project-URL: documentation, https://github.com/roknicmilos/django-pdf-view/blob/main/README.md
Project-URL: homepage, https://github.com/roknicmilos/django-pdf-view
Project-URL: issues, https://github.com/roknicmilos/django-pdf-view/issues
Project-URL: repository, https://github.com/roknicmilos/django-pdf-view/
